vcspack301/__init__.py
vcspack301/utils.py
vcspack300-0.1.dist-info/LICENSE.txt
vcspack300-0.1.dist-info/METADATA
vcspack300-0.1.dist-info/WHEEL
vcspack300-0.1.dist-info/top_level.txt
vcspack300-0.1.dist-info/RECORD
