Metadata-Version: 2.1
Name: vcspack300
Version: 0.1
Summary: vcspack utilities
Home-page: UNKNOWN
Author: rahul
Author-email: rahulst117@gmail.com
License: MIT
Platform: UNKNOWN
